uc_tftp/__init__.py
uc_tftp-0.0.1.dist-info/LICENSE
uc_tftp-0.0.1.dist-info/METADATA
uc_tftp-0.0.1.dist-info/WHEEL
uc_tftp-0.0.1.dist-info/top_level.txt
uc_tftp-0.0.1.dist-info/RECORD
