Metadata-Version: 2.1
Name: uc-tftp
Version: 0.0.1
Summary: Implementation of classes and functions for working with files via tftp.
Home-page: https://github.com/dentist128/uc_tftp
Author: Eduard S. Markelov
Author-email: markeloveduard@gmail.com
License: UNKNOWN
Platform: UNKNOWN
Classifier: Programming Language :: Python :: 3
Classifier: License :: OSI Approved :: GNU Affero General Public License v3
Classifier: Operating System :: OS Independent
Requires-Python: >=2.6, <4
